{
    "_comment": "Scenario 2: HD-Map Obstacle Avoidance — D* Lite planner through pre-mapped obstacle field with full perception+radar stack. Compare with scenario 18 which has no HD-map and relies entirely on runtime perception.",
    "scenario": {
        "name": "obstacle_avoidance",
        "description": "Navigate through a 4-obstacle field using D* Lite planner with HD-map static obstacles. Full perception stack (color_contour + ByteTrack + UKF radar fusion) runs in parallel to confirm/refresh HD-map entries and detect unexpected obstacles. Path-aware ObstacleAvoider3D provides lateral nudge. Validates HD-map + perception cooperation.",
        "tier": 2,
        "timeout_s": 150,
        "requires_gazebo": true
    },
    "config_overrides": {
        "mission_planner": {
            "takeoff_altitude_m": 5.0,
            "acceptance_radius_m": 3.0,
            "overshoot_proximity_factor": 5.0,
            "cruise_speed_mps": 1.5,
            "survey_duration_s": 0,
            "path_planner": {"backend": "dstar_lite", "max_search_time_ms": 1500, "max_iterations": 200000, "z_band_cells": 0, "replan_interval_s": 0.5, "look_ahead_m": 0.0, "smoothing_alpha": 0.5, "yaw_towards_travel": true, "yaw_smoothing_rate": 0.3, "snap_approach_bias": 1.0},
            "obstacle_avoider": {"backend": "potential_field_3d"},
            "obstacle_avoidance": {
                "min_distance_m": 2.0,
                "influence_radius_m": 8.0,
                "repulsive_gain": 3.0,
                "max_correction_mps": 1.5,
                "vertical_gain": 0.0,
                "path_aware": true,
                "_comment": "D* Lite is primary avoidance. Avoider is safety net: 8m influence, 1.5 max correction (100% of cruise), gain=3.0.",
                "_comment_706": "Issue #706 — turn OFF the scenario-33 safety nets so this Gazebo scenario runs with legacy main-branch avoider behaviour for empirical comparison.",
                "close_regime_final_clamp": false,
                "aabb_aware_distance": false
            },
            "occupancy_grid": {
                "resolution_m": 2.0,
                "inflation_radius_m": 2.0,
                "dynamic_obstacle_ttl_s": 1.0,
                "min_confidence": 0.4,
                "promotion_hits": 8,
                "min_promotion_depth_confidence": 0.8,
                "max_static_cells": 800,
                "prediction_enabled": false,
                "_comment": "2m grid, 2m inflation, 1.0s TTL. promotion_hits=8: filters transient detections (0.4s at 20Hz) before promoting to static. HD-map suppression (Issue #389) prevents duplicating cells near pre-mapped obstacles. max_static_cells=800 safety cap. prediction_enabled=false: camera-depth noise makes velocity extrapolation unreliable (Issue #340), and HD-map already provides obstacle positions."
            },
            "static_obstacles": [
                {"x": 3,  "y": 15, "radius_m": 1.0, "height_m": 1.7, "_color": "RED"},
                {"x": 10, "y": 10, "radius_m": 1.0, "height_m": 6.0, "_color": "GREEN"},
                {"x": 18, "y": 5,  "radius_m": 0.8, "height_m": 2.0, "_color": "BLUE"},
                {"x": 5,  "y": 3,  "radius_m": 0.75, "height_m": 10.0, "_color": "ORANGE"}
            ],
            "_comment_static_obstacles": "HD-map matching the 4 physical obstacles in test_world.sdf. Camera+radar detections confirm these at runtime.",
            "geofence": {
                "enabled": false,
                "_comment": "Geofence disabled — D* Lite replanning may push drone toward boundary when avoiding obstacles"
            },
            "waypoints": [
                {"x": -4, "y": 22, "z": 4, "yaw": 1.57,  "speed": 1.5, "payload_trigger": false, "_comment": "Fly north — RED(3,15) 10.6m away. Wide margin for promoted cells."},
                {"x": 14, "y": 22, "z": 4, "yaw": 0,      "speed": 1.5, "payload_trigger": true,  "_comment": "Fly east — clear corridor north of obstacles. Payload trigger."},
                {"x": 22, "y": 14, "z": 4, "yaw": -1.0,   "speed": 1.5, "payload_trigger": false, "_comment": "Fly southeast — GREEN(10,10) 12.6m, BLUE(18,5) 9.8m."},
                {"x": 14, "y": -4, "z": 4, "yaw": -2.36,  "speed": 1.5, "payload_trigger": false, "_comment": "Fly southwest — ORANGE(5,3) 11.4m, BLUE(18,5) 9.8m."},
                {"x": 0,  "y": 0,  "z": 5, "yaw": -2.36,  "speed": 1.5, "payload_trigger": false, "_comment": "Return home — ORANGE(5,3) 5.8m away, outside promotion zone."}
            ],
            "_comment_waypoints": "5 waypoints routing near all 4 obstacles. Navigation WPs >8m from obstacle centres to account for HD-map footprint (4m) + runtime promoted cells (2-4m). Home WP (0,0) is 5.8m from ORANGE — acceptable since drone is landing."
        },
        "perception": {
            "detector": {
                "backend": "color_contour",
                "confidence_threshold": 0.3,
                "max_detections": 64
            },
            "tracker": {
                "backend": "bytetrack",
                "high_conf_threshold": 0.5,
                "low_conf_threshold": 0.1,
                "max_iou_cost": 0.7,
                "_comment": "ByteTrack two-stage association for robust obstacle tracking"
            },
            "radar": {
                "backend": "gazebo",
                "enabled": true,
                "update_rate_hz": 20,
                "ground_filter_alt_m": 2.0,
                "_comment": "Radar enabled — HAL ground filter at 2.0m AGL rejects noise-elevated ground returns (Issue #340)"
            },
            "fusion": {
                "backend": "ukf",
                "rate_hz": 30,
                "depth_scale": 1.0,
                "assumed_obstacle_height_m": 3.0,
                "height_priors": {"unknown": 3.0, "person": 1.7, "vehicle_car": 2.0, "vehicle_truck": 3.5, "drone": 0.3, "animal": 0.8, "building": 10.0, "tree": 6.0},
                "radar": {
                    "enabled": true,
                    "ground_filter_enabled": true,
                    "min_object_altitude_m": 1.5,
                    "altitude_gate_m": 2.0,
                    "_comment": "Camera+radar UKF fusion with ground filter + altitude gate"
                }
            },
            "path_a": {
                "_comment_706": "Issue #706 — explicitly disable PR #647 voxel-snapshot append for legacy main-parity. PATH A is already disabled by default in this scenario (color_contour detector, no SAM), so this is documentation more than functional change.",
                "avoider_surface": {
                    "enabled": false
                }
            }
        }
    },
    "fault_sequence": {
        "steps": []
    },
    "pass_criteria": {
        "log_contains": [
            "Path planner: DStarLitePlanner",
            "Obstacle avoider: ObstacleAvoider3D",
            "backend: bytetrack",
            "ground_filter_alt_m",
            "TAKEOFF",
            "NAVIGATE",
            "EXECUTING",
            "Mission complete"
        ],
        "log_must_not_contain": [
            "EMERGENCY_LAND",
            "OBSTACLE COLLISION"
        ],
        "processes_alive": [
            "video_capture", "perception", "slam_vio_nav",
            "mission_planner", "comms", "payload_manager", "system_monitor"
        ]
    }
}
